Workbook

Sheet Portada
B4: REPOSITORIO ZELLE · Mes en curso (Mayo 2026)
B5: Demo creado por ZENIA · zeniapartners.com · Datos ficticios (cliente y operacion inventados)
B7: EFECTIVO TRAZADO TOTAL
B8: =C12+E12+G12
B9: Suma trazada: liquido en banco + capital en gandolas + cuentas por cobrar
B10: SALDO INICIAL BANCO (editable): | E10: 35000
B11: EFECTIVO EN BANCO | D11: DINERO EN GANDOLAS | F11: CUENTAS POR COBRAR | H11: TOTAL TRAZADO
B12: =E10+SUMIFS(Transacciones!D:D,Transacciones!E:E,"in")-SUMIFS(Transacciones!D:D,Transacciones!E:E,"out")-(SUMIFS(Transacciones!D:D,Transacciones!F:F,"entrega_gandola")-SUMIFS(Transacciones!D:D,Transacciones!F:F,"retorno_gandola"))-(SUMIFS(Transacciones!D:D,Transacciones!F:F,"venta_credito")-SUMIFS(Transacciones!D:D,Transacciones!F:F,"cobro_credito")) | D12: =SUMIFS(Transacciones!D:D,Transacciones!F:F,"entrega_gandola")-SUMIFS(Transacciones!D:D,Transacciones!F:F,"retorno_gandola") | F12: =SUMIFS(Transacciones!D:D,Transacciones!F:F,"venta_credito")-SUMIFS(Transacciones!D:D,Transacciones!F:F,"cobro_credito") | H12: =C12+E12+G12
B13: Saldo liquido | D13: Capital en transito | F13: Pendiente de cobrar | H13: Suma de los 3
B15: KPIs DEL PERIODO
B17: INGRESOS COBRADOS | D17: GASTOS PAGADOS | F17: FLUJO NETO | H17: TICKET PROMEDIO
B18: =SUMIFS(Transacciones!D:D,Transacciones!E:E,"in") | D18: =SUMIFS(Transacciones!D:D,Transacciones!E:E,"out") | F18: =C18-E18 | H18: =IFERROR(C18/COUNTIFS(Transacciones!E:E,"in"),0)
B19: Total in | D19: Total out | F19: Cashflow del periodo | H19: Por cobro
B21: ALERTAS Y RESUMEN OPERATIVO
B23: ! GANDOLAS ACTIVAS | E23: ! PROXIMO PAGO INTERES | G23: + COBROS ESTA SEMANA
B24: =COUNTIFS(Transacciones!F:F,"entrega_gandola")-COUNTIFS(Transacciones!F:F,"retorno_gandola") | E24: 1600 | G24: =COUNTIFS(Transacciones!E:E,"in")
B25: Capital en ruta sin cerrar | E25: Luis Mendoza · vence 28-MAY | G25: Pagos recibidos
B27: TOP PAGADORES DEL PERIODO
B28: Cliente | D28: Total Cobrado | F28: # Pagos | H28: Ticket Promedio
B29: Carlos Perez | D29: 1200 | F29: 2 | H29: 600
B30: Empresa XYZ | D30: 1700 | F30: 2 | H30: 850
B31: Lucia Ramirez | D31: 1300 | F31: 2 | H31: 650
B32: Pedro Lopez | D32: 800 | F32: 2 | H32: 400
B33: Maria Gonzalez | D33: 500 | F33: 1 | H33: 500
B34: Restaurante Lima | D34: 450 | F34: 1 | H34: 450

Sheet Transacciones
A1: ID | B1: Fecha | C1: Nombre | D1: Monto | E1: Direccion | F1: Categoria | G1: Conf# | H1: Estado | I1: Notas
A2: D-001 | B2: 2026-05-04 | C2: Maria Gonzalez | D2: 500 | E2: in | F2: cobro_cliente | G2: ABC123XYZ | H2: completed | I2: Pago anticipo orden #4421
A3: D-002 | B3: 2026-05-03 | C3: Carlos Perez | D3: 700 | E3: in | F3: cobro_cliente | G3: XYZ789DEF | H3: completed | I3: Pago final pedido botellas
A4: D-003 | B4: 2026-05-03 | C4: Empresa XYZ | D4: 850 | E4: in | F4: cobro_cliente | G4: QWE456RTY | H4: completed | I4: Pago factura mayo
A5: D-004 | B5: 2026-05-02 | C5: Carlos Perez | D5: 500 | E5: in | F5: cobro_cliente | G5: MNB789POI | H5: completed | I5: Anticipo pedido grande
A6: D-005 | B6: 2026-05-02 | C6: Lucia Ramirez | D6: 650 | E6: in | F6: cobro_cliente | G6: ZXC123ASD | H6: completed | I6: Pago semanal restaurante
A7: D-006 | B7: 2026-05-01 | C7: Gandola Beleva | D7: 5000 | E7: out | F7: entrega_gandola | H7: completed | I7: Capital viaje Caracas - flete + impuestos
A8: D-007 | B8: 2026-05-01 | C8: Pedro Lopez | D8: 400 | E8: in | F8: cobro_cliente | G8: WER567TYU | H8: completed | I8: Pago tienda esquina
A9: D-008 | B9: 2026-04-30 | C9: Juan Rodriguez | D9: 800 | E9: out | F9: venta_credito | H9: completed | I9: Mercancia paga el 15 de mayo
A10: D-009 | B10: 2026-04-30 | C10: Planilla Equipo | D10: 2500 | E10: out | F10: planilla | H10: completed | I10: Quincena fin abril
A11: D-010 | B11: 2026-04-29 | C11: Aduana DAE | D11: 1350 | E11: out | F11: impuesto_gandola | H11: completed | I11: Permiso ingreso Venezuela
A12: D-011 | B12: 2026-04-28 | C12: Luis Mendoza | D12: 1600 | E12: out | F12: pago_deuda_interes | H12: completed | I12: Interes mensual abril (4%)
A13: D-012 | B13: 2026-04-28 | C13: Pedro Ramos | D13: 2500 | E13: out | F13: pago_deuda_interes | H13: completed | I13: Interes mensual abril (5%)
A14: D-013 | B14: 2026-04-27 | C14: Logistica Andes | D14: 2800 | E14: out | F14: gasto_logistica | G14: WT2026050108821 | H14: completed | I14: Flete contenedor #C-2204
A15: D-014 | B15: 2026-04-26 | C15: Gandola Beleva | D15: 4200 | E15: in | F15: retorno_gandola | H15: completed | I15: Cierre viaje Caracas - efectivo
A16: D-015 | B16: 2026-04-25 | C16: Viaticos chofer | D16: 320 | E16: out | F16: viaticos | H16: completed | I16: Comida + peajes Caracas
A17: D-016 | B17: 2026-04-25 | C17: Lucia Ramirez | D17: 650 | E17: in | F17: cobro_cliente | G17: POI234UYT | H17: completed | I17: Pago semanal restaurante
A18: D-017 | B18: 2026-04-24 | C18: Empresa XYZ | D18: 850 | E18: in | F18: cobro_cliente | G18: LKJ567HGF | H18: completed | I18: Pago factura abril
A19: D-018 | B19: 2026-04-24 | C19: Almacen Doral | D19: 780 | E19: out | F19: alquiler | H19: completed | I19: Renta mayo galpon
A20: D-019 | B20: 2026-04-23 | C20: Pedro Lopez | D20: 400 | E20: in | F20: cobro_cliente | G20: MNB456VCX | H20: completed | I20: Pago semanal
A21: D-020 | B21: 2026-04-22 | C21: Restaurante Lima | D21: 450 | E21: in | F21: cobro_cliente | G21: QAZ123WSX | H21: completed | I21: Pago primera caja
A22: D-021 | B22: 2026-04-22 | C22: Combustible flota | D22: 240 | E22: out | F22: combustible | H22: completed | I22: Gasolina 2 furgonetas
A23: D-022 | B23: 2026-04-21 | C23: Gandola Beleva | D23: 4500 | E23: out | F23: entrega_gandola | H23: completed | I23: Capital nuevo viaje Maracaibo
A24: D-023 | B24: 2026-04-20 | C24: Asesoria Contable | D24: 480 | E24: out | F24: honorarios | H24: completed | I24: Honorarios mensuales
A25: D-024 | B25: 2026-04-19 | C25: Carmona (cliente) | D25: 650 | E25: in | F25: cobro_credito | G25: VBN234ZAQ | H25: completed | I25: Cancela mercancia entregada el 5 abr
A26: D-025 | B26: 2026-04-18 | C26: Telefonia movil | D26: 85 | E26: out | F26: servicios | H26: completed | I26: Plan business Verizon

Sheet Cashflow
B2: CASHFLOW DIARIO · Mayo 2026
B3: Movimientos consolidados por fecha. Ingresos / Gastos / Flujo / Saldo acumulado. | I3: Saldo inicial (Portada!E10): | J3: =Portada!E10
B5: Fecha | C5: Ingresos | D5: Gastos | E5: Flujo Neto | F5: Saldo Acumulado
B6: 2026-04-22 | C6: =SUMIFS(Transacciones!D:D,Transacciones!E:E,"in",Transacciones!B:B,"2026-04-22") | D6: =SUMIFS(Transacciones!D:D,Transacciones!E:E,"out",Transacciones!B:B,"2026-04-22") | E6: =C6-D6 | F6: =$J$3+E6
B7: 2026-04-23 | C7: =SUMIFS(Transacciones!D:D,Transacciones!E:E,"in",Transacciones!B:B,"2026-04-23") | D7: =SUMIFS(Transacciones!D:D,Transacciones!E:E,"out",Transacciones!B:B,"2026-04-23") | E7: =C7-D7 | F7: =F6+E7
B8: 2026-04-24 | C8: =SUMIFS(Transacciones!D:D,Transacciones!E:E,"in",Transacciones!B:B,"2026-04-24") | D8: =SUMIFS(Transacciones!D:D,Transacciones!E:E,"out",Transacciones!B:B,"2026-04-24") | E8: =C8-D8 | F8: =F7+E8
B9: 2026-04-25 | C9: =SUMIFS(Transacciones!D:D,Transacciones!E:E,"in",Transacciones!B:B,"2026-04-25") | D9: =SUMIFS(Transacciones!D:D,Transacciones!E:E,"out",Transacciones!B:B,"2026-04-25") | E9: =C9-D9 | F9: =F8+E9
B10: 2026-04-26 | C10: =SUMIFS(Transacciones!D:D,Transacciones!E:E,"in",Transacciones!B:B,"2026-04-26") | D10: =SUMIFS(Transacciones!D:D,Transacciones!E:E,"out",Transacciones!B:B,"2026-04-26") | E10: =Portada!E10 | F10: =F9+E10
B11: 2026-04-27 | C11: =SUMIFS(Transacciones!D:D,Transacciones!E:E,"in",Transacciones!B:B,"2026-04-27") | D11: =SUMIFS(Transacciones!D:D,Transacciones!E:E,"out",Transacciones!B:B,"2026-04-27") | E11: =C11-D11 | F11: =F10+E11
B12: 2026-04-28 | C12: =SUMIFS(Transacciones!D:D,Transacciones!E:E,"in",Transacciones!B:B,"2026-04-28") | D12: =SUMIFS(Transacciones!D:D,Transacciones!E:E,"out",Transacciones!B:B,"2026-04-28") | E12: =C12-D12 | F12: =F11+E12
B13: 2026-04-29 | C13: =SUMIFS(Transacciones!D:D,Transacciones!E:E,"in",Transacciones!B:B,"2026-04-29") | D13: =SUMIFS(Transacciones!D:D,Transacciones!E:E,"out",Transacciones!B:B,"2026-04-29") | E13: =C13-D13 | F13: =F12+E13
B14: 2026-04-30 | C14: =SUMIFS(Transacciones!D:D,Transacciones!E:E,"in",Transacciones!B:B,"2026-04-30") | D14: =SUMIFS(Transacciones!D:D,Transacciones!E:E,"out",Transacciones!B:B,"2026-04-30") | E14: =C14-D14 | F14: =F13+E14
B15: 2026-05-01 | C15: =SUMIFS(Transacciones!D:D,Transacciones!E:E,"in",Transacciones!B:B,"2026-05-01") | D15: =SUMIFS(Transacciones!D:D,Transacciones!E:E,"out",Transacciones!B:B,"2026-05-01") | E15: =C15-D15 | F15: =F14+E15
B16: 2026-05-02 | C16: =SUMIFS(Transacciones!D:D,Transacciones!E:E,"in",Transacciones!B:B,"2026-05-02") | D16: =SUMIFS(Transacciones!D:D,Transacciones!E:E,"out",Transacciones!B:B,"2026-05-02") | E16: =C16-D16 | F16: =F15+E16
B17: 2026-05-03 | C17: =SUMIFS(Transacciones!D:D,Transacciones!E:E,"in",Transacciones!B:B,"2026-05-03") | D17: =SUMIFS(Transacciones!D:D,Transacciones!E:E,"out",Transacciones!B:B,"2026-05-03") | E17: =C17-D17 | F17: =F16+E17
B18: 2026-05-04 | C18: =SUMIFS(Transacciones!D:D,Transacciones!E:E,"in",Transacciones!B:B,"2026-05-04") | D18: =SUMIFS(Transacciones!D:D,Transacciones!E:E,"out",Transacciones!B:B,"2026-05-04") | E18: =C18-D18 | F18: =F17+E18
B19: TOTAL PERIODO | C19: =SUM(C6:C18) | D19: =SUM(D6:D18) | E19: =C19-D19 | F19: =F18

Sheet Deudas
A1: DEUDAS · Por cobrar / Por pagar
A3: Deudor / Acreedor | B3: Tipo | C3: Capital Original | D3: Fecha Inicio | E3: Tasa Mensual % | F3: Meses Transc. | G3: Interes Mensual Fijo | H3: Pagos a Capital | I3: Saldo Vivo | J3: Fecha Vcto. | K3: Dias p/Vcto. | L3: Forma de Pago | M3: Status | N3: Notas
A4: Luis Mendoza | B4: Por Pagar | C4: 40000 | D4: 2025-12-15 | E4: 4 | F4: 4 | G4: 1600 | H4: 0 | I4: 40000 | L4: Transferencia mensual | M4: Sin vcto. | N4: Prestamo dic 2025. Capital $40,000. Interes 4% mensual fijo $1,600. Solo se pagan intereses; capital intacto.
A5: Pedro Ramos | B5: Por Pagar | C5: 50000 | D5: 2025-12-15 | E5: 5 | F5: 4 | G5: 2500 | H5: 0 | I5: 50000 | L5: Transferencia mensual | M5: Sin vcto. | N5: Prestamo dic 2025. Capital $50,000. Interes 5% mensual fijo $2,500. Solo se pagan intereses; capital intacto.
A10: TOTAL POR PAGAR | C10: 90000 | G10: 4100 | I10: 90000
A14: CREDITO ROTATIVO PROVEEDOR
A15: Proveedor | B15: Cisterna Pendiente | C15: Monto | D15: Fecha Entrega
A16: Olivar Andaluz S.L. | B16: Cisterna 18 (OL180) | C16: 58420.5 | D16: 2026-05-22

Sheet KPIs
B2: KPIs (referencia tecnica)
B5: Total Ingresos | C5: =SUMIFS(Transacciones!D:D,Transacciones!E:E,"in")
B6: Total Gastos | C6: =SUMIFS(Transacciones!D:D,Transacciones!E:E,"out")
B7: Flujo Neto | C7: =C5-C6
B8: # Cobros | C8: =COUNTIFS(Transacciones!E:E,"in")
B9: # Pagos | C9: =COUNTIFS(Transacciones!E:E,"out")
B10: Banco (calculado) | C10: =Portada!C12
B11: Gandolas (calculado) | C11: =Portada!E12
B12: Por Cobrar (calculado) | C12: =Portada!G12
B13: Total Trazado | C13: =Portada!B8
